psql2rabbitmq/__init__.py
psql2rabbitmq-1.0.6.6.data/scripts/psql2rabbitmq
psql2rabbitmq-1.0.6.6.dist-info/METADATA
psql2rabbitmq-1.0.6.6.dist-info/WHEEL
psql2rabbitmq-1.0.6.6.dist-info/top_level.txt
psql2rabbitmq-1.0.6.6.dist-info/RECORD
