Metadata-Version: 2.1
Name: psql2rabbitmq
Version: 1.0.6.6
Summary: Asynchronous PostgreSQL data read and publish to RabbitMQ library
Home-page: https://github.com/mantis-software-company/psql2rabbitmq
Author: Umit YILMAZ
Author-email: umutyilmaz44@gmail.com
License: UNKNOWN
Platform: all
Classifier: License :: OSI Approved :: Apache Software License
Classifier: Topic :: Internet
Classifier: Topic :: Software Development
Classifier: Topic :: Software Development :: Libraries
Classifier: Topic :: Software Development :: Testing
Classifier: Intended Audience :: Developers
Classifier: Operating System :: MacOS
Classifier: Operating System :: POSIX
Classifier: Operating System :: Microsoft
Classifier: Programming Language :: Python
Classifier: Programming Language :: Python :: 3.7
Classifier: Programming Language :: Python :: 3.8
Requires-Python: >3.6.*, <4
Requires-Dist: aiopg
Requires-Dist: aio-pika
Requires-Dist: jinja2
Requires-Dist: psycopg2-binary
